formatscaper/__init__.py
formatscaper/models.py
formatscaper/utils.py
formatscaper/cli/__init__.py
formatscaper/cli/formatscaper.py
formatscaper/cli/resultman.py
formatscaper-0.1.0.dist-info/LICENSE
formatscaper-0.1.0.dist-info/METADATA
formatscaper-0.1.0.dist-info/WHEEL
formatscaper-0.1.0.dist-info/entry_points.txt
formatscaper-0.1.0.dist-info/top_level.txt
formatscaper-0.1.0.dist-info/RECORD
