Metadata-Version: 2.1
Name: formatscaper
Version: 0.1.0
Summary: Tool for building an overview of the file format landscape in a research data repository.
Author-email: Maximilian Moser <maximilian.moser@tuwien.ac.at>
Project-URL: Repository, https://gitlab.tuwien.ac.at/fairdata/formatscaper
Classifier: Development Status :: 3 - Alpha
Classifier: License :: OSI Approved :: MIT License
Classifier: Intended Audience :: Developers
Classifier: Intended Audience :: System Administrators
Classifier: Topic :: File Formats
Classifier: Topic :: Utilities
Classifier: Programming Language :: Python :: 3
Classifier: Programming Language :: Python :: 3.11
Classifier: Programming Language :: Python :: 3.12
Classifier: Operating System :: POSIX :: Linux
License-File: LICENSE
Requires-Dist: PyYAML >=6.0.1
Requires-Dist: progressbar2 >=4.4.2
Requires-Dist: urwid >=2.6.9
Requires-Dist: SQLAlchemy >=2.0
Provides-Extra: dev
Requires-Dist: black >=24.2.0 ; extra == 'dev'
Requires-Dist: isort >=5.13.2 ; extra == 'dev'
Requires-Dist: ipython >=8.22.2 ; extra == 'dev'
Requires-Dist: flake8 >=7.0 ; extra == 'dev'
Requires-Dist: flake8-pyproject >=1.2.3 ; extra == 'dev'
Provides-Extra: tests
Requires-Dist: pytest >=8.3 ; extra == 'tests'
Requires-Dist: pytest-black >=0.3 ; extra == 'tests'
Requires-Dist: pytest-cov >=5.0 ; extra == 'tests'
Requires-Dist: pytest-isort >=4.0 ; extra == 'tests'
